mdproscholdt/__init__.py
mdproscholdt/cli.py
mdproscholdt/config.py
mdproscholdt/easy.py
mdproscholdt/llm.py
mdproscholdt/prompts.py
mdproscholdt/scanner.py
mdproscholdt/summarize.py
mdproscholdt/writer.py
mdproscholdt-0.2.5.dist-info/licenses/LICENSE
mdproscholdt-0.2.5.dist-info/METADATA
mdproscholdt-0.2.5.dist-info/WHEEL
mdproscholdt-0.2.5.dist-info/entry_points.txt
mdproscholdt-0.2.5.dist-info/top_level.txt
mdproscholdt-0.2.5.dist-info/RECORD
