Metadata-Version: 2.4
Name: mdproscholdt
Version: 0.2.5
Summary: Gera documentação Markdown de um projeto usando (ou não) IA, com extração de docstrings/comentários.
Author: Henrique Proscholdt
Requires-Python: >=3.9
License-File: LICENSE
Requires-Dist: tomli; python_version < "3.11"
Requires-Dist: pathspec>=0.12.1
Requires-Dist: tqdm>=4.66.3
Requires-Dist: pydantic>=2.8
Requires-Dist: rich>=13.8
Requires-Dist: jinja2>=3.1
Requires-Dist: python-slugify>=8.0
Requires-Dist: openai>=1.40.0
Dynamic: license-file
